pyedflib/__init__.py
pyedflib/edfreader.py
pyedflib/edfwriter.py
pyedflib/highlevel.py
pyedflib/py.typed
pyedflib/version.py
pyedflib/_extensions/__init__.py
pyedflib/_extensions/_pyedflib.cpython-39-i386-linux-gnu.so
pyedflib/_extensions/_pyedflib.pyi
pyedflib/data/__init__.py
pyedflib/data/_readers.py
pyedflib/data/test_generator.edf
pyedflib/tests/test_doc.py
pyedflib/tests/test_edfreader.py
pyedflib/tests/test_edfwriter.py
pyedflib/tests/test_highlevel.py
pyedflib/tests/data/test_generator.bdf
pyedflib/tests/data/test_generator.edf
pyedflib/tests/data/test_generator_datarec_generator_0_5.bdf
pyedflib/tests/data/test_generator_datarec_generator_2.bdf
pyedflib/tests/data/test_legacy.edf
pyedflib/tests/data/test_subsecond.edf
pyedflib/tests/data/test_utf8.edf
pyedflib-0.1.42.dist-info/METADATA
pyedflib-0.1.42.dist-info/WHEEL
pyedflib-0.1.42.dist-info/top_level.txt
pyedflib-0.1.42.dist-info/RECORD
pyedflib-0.1.42.dist-info/licenses/LICENSE
