Metadata-Version: 2.1
Name: pyEDFlib
Version: 0.1.42
Summary: library to read/write EDF+/BDF+ files
Home-page: https://github.com/holgern/pyedflib
Author: Holger Nahrstaedt
Author-email: nahrstaedt@gmail.com
Maintainer: Holger Nahrstaedt
Maintainer-email: nahrstaedt@gmail.com
License: BSD
Keywords: EDFlib,European data format,EDF,BDF,EDF+,BDF+
Platform: Windows
Platform: Linux
Platform: Solaris
Platform: Mac OS-X
Platform: Unix
Classifier: Development Status :: 5 - Production/Stable
Classifier: Intended Audience :: Developers
Classifier: Intended Audience :: Education
Classifier: Intended Audience :: Science/Research
Classifier: License :: OSI Approved :: BSD License
Classifier: Operating System :: OS Independent
Classifier: Programming Language :: Python :: Implementation :: CPython
Classifier: Programming Language :: C
Classifier: Programming Language :: Python
Classifier: Programming Language :: Python :: 3
Classifier: Programming Language :: Python :: 3.8
Classifier: Programming Language :: Python :: 3.9
Classifier: Programming Language :: Python :: 3.10
Classifier: Programming Language :: Python :: 3.11
Classifier: Programming Language :: Python :: 3.12
Classifier: Programming Language :: Python :: 3.13
Classifier: Topic :: Software Development :: Libraries :: Python Modules
License-File: LICENSE
Requires-Dist: numpy >=1.9.1
